keyrings/__init__.py
keyrings/pyx_keyring.py
pyx_keyring-0.1.0.dist-info/entry_points.txt
pyx_keyring-0.1.0.dist-info/licenses/LICENSE
pyx_keyring-0.1.0.dist-info/WHEEL
pyx_keyring-0.1.0.dist-info/METADATA
pyx_keyring-0.1.0.dist-info/RECORD
