Metadata-Version: 2.4
Name: pyx-keyring
Version: 0.1.0
Summary: A keyring plugin for pyx.
Keywords: pyx,keyring
Author-email: "Astral Software Inc." <hey@astral.sh>
Requires-Python: >=3.7
License-Expression: MIT
Classifier: Programming Language :: Python :: 3
Classifier: Programming Language :: Python :: 3.7
Classifier: Programming Language :: Python :: 3.8
Classifier: Programming Language :: Python :: 3.9
Classifier: Programming Language :: Python :: 3.10
Classifier: Programming Language :: Python :: 3.11
Classifier: Programming Language :: Python :: 3.12
Classifier: Programming Language :: Python :: 3.13
Classifier: Programming Language :: Python :: 3.14
License-File: LICENSE
Requires-Dist: keyring
